bioreqs/__init__.py
bioreqs/ncbi.py
bioreqs/py.typed
bioreqs-0.1.0.dev3.dist-info/WHEEL
bioreqs-0.1.0.dev3.dist-info/METADATA
bioreqs-0.1.0.dev3.dist-info/RECORD
